odoo/addons/product_pricelist_print_website_sale/README.rst
odoo/addons/product_pricelist_print_website_sale/__init__.py
odoo/addons/product_pricelist_print_website_sale/__manifest__.py
odoo/addons/product_pricelist_print_website_sale/i18n/es.po
odoo/addons/product_pricelist_print_website_sale/i18n/it.po
odoo/addons/product_pricelist_print_website_sale/i18n/product_pricelist_print_website_sale.pot
odoo/addons/product_pricelist_print_website_sale/readme/CONTRIBUTORS.rst
odoo/addons/product_pricelist_print_website_sale/readme/DESCRIPTION.rst
odoo/addons/product_pricelist_print_website_sale/readme/USAGE.rst
odoo/addons/product_pricelist_print_website_sale/static/description/icon.png
odoo/addons/product_pricelist_print_website_sale/static/description/index.html
odoo/addons/product_pricelist_print_website_sale/wizards/__init__.py
odoo/addons/product_pricelist_print_website_sale/wizards/product_pricelist_print.py
odoo/addons/product_pricelist_print_website_sale/wizards/product_pricelist_print_view.xml
odoo12_addon_product_pricelist_print_website_sale-12.0.1.0.0.99.dev5.dist-info/METADATA
odoo12_addon_product_pricelist_print_website_sale-12.0.1.0.0.99.dev5.dist-info/WHEEL
odoo12_addon_product_pricelist_print_website_sale-12.0.1.0.0.99.dev5.dist-info/top_level.txt
odoo12_addon_product_pricelist_print_website_sale-12.0.1.0.0.99.dev5.dist-info/RECORD
